<?xml version="1.0" encoding="UTF-8"?>
<objects serializationModel="Studio.02.02.00">
	<object class="AudioFile" id="{176cb28d-9c83-42de-b6a4-3f33d043ed25}">
		<property name="assetPath">
			<value>Interactable_objects/soldier_die_var03.wav</value>
		</property>
		<property name="frequencyInKHz">
			<value>48</value>
		</property>
		<property name="channelCount">
			<value>2</value>
		</property>
		<property name="length">
			<value>0.88920833333333338</value>
		</property>
		<relationship name="masterAssetFolder">
			<destination>{165a6e82-17b4-42f1-98d1-9c0a5edfc6ab}</destination>
		</relationship>
	</object>
</objects>
