<?xml version="1.0" encoding="UTF-8"?>
<objects serializationModel="Studio.02.02.00">
	<object class="AudioFile" id="{9ecf7af9-e677-48b4-a672-c76f35aabfc3}">
		<property name="assetPath">
			<value>UI/button_recruit.wav</value>
		</property>
		<property name="frequencyInKHz">
			<value>48</value>
		</property>
		<property name="channelCount">
			<value>2</value>
		</property>
		<property name="length">
			<value>0.77114583333333331</value>
		</property>
		<relationship name="masterAssetFolder">
			<destination>{165a6e82-17b4-42f1-98d1-9c0a5edfc6ab}</destination>
		</relationship>
	</object>
</objects>
